{
  "categorias": [
    {
      "id": 1,
      "titulo": "Development",
      "cor": "#6BD1FF",
      "link_extra": {
        "text": "Torne-se um Desenvolvedor Profissional",
        "url": "https://www.alura.com.br"
      }
    },
    {
      "id": 2,
      "titulo": "Games",
      "cor": "#00C86F",
      "link_extra": {
        "text": "O Melhor Jogo do Mundo",
        "url": "https://www.nintendo.pt/Jogos/Super-Nintendo/Super-Mario-World-752133.html"
      }
    },
    {
      "id": 3,
      "titulo": "Entertainment",
      "cor": "#9cd33b",
      "link_extra": {
        "text": "O Lugar mais Divertido do Mundo",
        "url": "https://disneyworld.disney.go.com/pt-br"
      }
    },
    {
      "id": 4,
      "titulo": "Gastronomy",
      "cor": "orange",
      "link_extra": {
        "text": "Torne-se um Chef Profissional",
        "url": "https://www.cordonbleu.edu/home/pt-br"
      }
    },
    {
      "id": 5,
      "titulo": "Gym",
      "cor": "red",
      "link_extra": {
        "text": "O Maior Movimento Educacional da Musculação no Brasil",
        "url": "https://universidademaromba.com/"
      }
    },
    {
      "id": 6,
      "titulo": "Sports",
      "cor": "#6b5be2",
      "link_extra": {
        "text": "A Melhor Marca de Tênis do Mundo",
        "url": "https://air.jordan.com/card/the-most-memorable-shoes-worn-by-mj-in-the-last-dance"
      }
    }
  ],
  "videos": [
    {
      "id": 1,
      "categoriaId": 1,
      "titulo": "What is Love?",
      "url": "https://www.youtube.com/watch?v=9tVkWYv484Y"
    },
    {
      "id": 2,
      "categoriaId": 1,
      "titulo": "O que é JavaScript?",
      "url": "https://www.youtube.com/watch?v=NaVSbnnV75Q&t=63s"
    },
    {
      "id": 3,
      "categoriaId": 1,
      "titulo": "Eu quero saber se você consegue responder essas 3 perguntas de JavaScript!",
      "url": "https://www.youtube.com/watch?v=QVrrqgDhhu4"
    },
    {
      "id": 4,
      "categoriaId": 1,
      "titulo": "Node.js: Iniciando da teoria à prática",
      "url": "https://www.youtube.com/watch?v=DiXbJL3iWVs&t=1s"
    },
    {
      "id": 5,
      "categoriaId": 1,
      "titulo": "Dark e Light Mode Nativos com React Native e Styled Components!",
      "url": "https://www.youtube.com/watch?v=MdysIsBvTEQ"
    },
    {
      "id": 6,
      "categoriaId": 1,
      "titulo": "O que estudar antes de tentar aprender um Framework JavaScript?",
      "url": "https://www.youtube.com/watch?v=QzDjdlF1BQI"
    },
    {
      "id": 7,
      "categoriaId": 1,
      "titulo": "Programamos uma Ferramenta pro Youtube com JavaScript Puro",
      "url": "https://www.youtube.com/watch?v=ScGwWsoC_-I"
    },
    {
      "id": 8,
      "categoriaId": 1,
      "titulo": "Como usar Git e Github na prática: Guia para iniciantes",
      "url": "https://www.youtube.com/watch?v=2alg7MQ6_sI"
    },
    {
      "id": 9,
      "categoriaId": 2,
      "titulo": "LEAGUE OF LEGENDS – Movie All Cinematics Trailer",
      "url": "https://www.youtube.com/watch?v=QamiN6atvw0"
    },
    {
      "id": 10,
      "categoriaId": 2,
      "titulo": "Teamfight Tactics - Trailer de Mecânica de Jogo - League of Legends",
      "url": "https://www.youtube.com/watch?v=_XbhPF2jTC0"
    },
    {
      "id": 11,
      "categoriaId": 2,
      "titulo": "A Rodada - Prévia de jogo de Valorant",
      "url": "https://www.youtube.com/watch?v=g8amyzDHOKw"
    },
    {
      "id": 12,
      "categoriaId": 2,
      "titulo": "Legends of Runeterra, the League of Legends Strategy Card Game",
      "url": "https://www.youtube.com/watch?v=61v6teDFv5E"
    },
    {
      "id": 13,
      "categoriaId": 2,
      "titulo": "Trailer de Anúncio Oficial do FIFA 21",
      "url": "https://www.youtube.com/watch?v=tuLAn9adQpI"
    },
    {
      "id": 14,
      "categoriaId": 2,
      "titulo": "Call of Duty®: Warzone - Official Trailer",
      "url": "https://www.youtube.com/watch?v=0E44DClsX5Q"
    },
    {
      "id": 15,
      "categoriaId": 2,
      "titulo": "Grand Theft Auto V Trailer",
      "url": "https://www.youtube.com/watch?v=QkkoHAzjnUs"
    },
    {
      "id": 16,
      "categoriaId": 3,
      "titulo": "F.R.I.E.N.D.S - Opening Season 1",
      "url": "https://www.youtube.com/watch?v=sLisEEwYZvw"
    },
    {
      "id": 17,
      "categoriaId": 3,
      "titulo": "People's Choice Awards- The Big Bang Theory",
      "url": "https://www.youtube.com/watch?v=hXHIUjAItyc"
    },
    {
      "id": 18,
      "categoriaId": 3,
      "titulo": "Romance Is Hard | Official Trailer? | Brooklyn Nine-Nine",
      "url": "https://www.youtube.com/watch?v=RKVxp9kRx3o"
    },
    {
      "id": 19,
      "categoriaId": 3,
      "titulo": "Toy Story 4 | Official Trailer",
      "url": "https://www.youtube.com/watch?v=wmiIUN-7qhE"
    },
    {
      "id": 20,
      "categoriaId": 3,
      "titulo": "Disney's Aladdin Teaser Trailer - In Theaters May 24th, 2019",
      "url": "https://www.youtube.com/watch?v=9g5knnlF7Zo"
    },
    {
      "id": 21,
      "categoriaId": 3,
      "titulo": "Coco Official Final Trailer",
      "url": "https://www.youtube.com/watch?v=Rvr68u6k5sI"
    },
    {
      "id": 22,
      "categoriaId": 3,
      "titulo": "Disney's Mulan | Final Trailer",
      "url": "https://www.youtube.com/watch?v=R-eFm--k21c"
    },
    {
      "id": 23,
      "categoriaId": 4,
      "titulo": "Stroganoff, com A mesmo!",
      "url": "https://www.youtube.com/watch?v=8qFZ0N4R68k"
    },
    {
      "id": 24,
      "categoriaId": 4,
      "titulo": "O VERDADEIRO PETIT GÂTEAU",
      "url": "https://www.youtube.com/watch?v=WwETLi0Lhv4"
    },
    {
      "id": 25,
      "categoriaId": 4,
      "titulo": "CHEF FOGAÇA VS HENRIQUE - FAROFA DE PÃO",
      "url": "https://www.youtube.com/watch?v=i_iQVgq2ZcQ"
    },
    {
      "id": 26,
      "categoriaId": 4,
      "titulo": "PIPOCA COM PÃO DE QUEIJO E BACON",
      "url": "https://www.youtube.com/watch?v=OOI9i2A9EcU"
    },
    {
      "id": 27,
      "categoriaId": 4,
      "titulo": "COMO FAZER COOKIE COM GOTAS DE CHOCOLATE",
      "url": "https://www.youtube.com/watch?v=KIqairdeHoM"
    },
    {
      "id": 28,
      "categoriaId": 4,
      "titulo": "Acabam pedindo todos os tacos do menu",
      "url": "https://www.youtube.com/watch?v=c0S6Z_4RoiM"
    },
    {
      "id": 29,
      "categoriaId": 4,
      "titulo": "LASANHA TRANÇADA DE PRESUNTO E QUEIJO",
      "url": "https://www.youtube.com/watch?v=IHkGFhg8tUI"
    },
    {
      "id": 30,
      "categoriaId": 5,
      "titulo": "TUDO SOBRE DIETA FLEXÍVEL",
      "url": "https://www.youtube.com/watch?v=GTIoj87CR1c"
    },
    {
      "id": 31,
      "categoriaId": 5,
      "titulo": "PERIODIZAÇÃO NA MUSCULAÇÃO",
      "url": "https://www.youtube.com/watch?v=vot2Q6a4D2M"
    },
    {
      "id": 32,
      "categoriaId": 5,
      "titulo": "SUPLEMENTOS PARA INICIANTES: O QUE TOMAR??",
      "url": "https://www.youtube.com/watch?v=MRU-WXnDUfA"
    },
    {
      "id": 33,
      "categoriaId": 5,
      "titulo": "BÌCEPS E TRÍCEPS BÁSICO E DESTRUIDOR",
      "url": "https://www.youtube.com/watch?v=sv5g_YxU8JI"
    },
    {
      "id": 34,
      "categoriaId": 5,
      "titulo": "COMO PERDER BARRIGA!? Passo a passo definitivo! 💪falso magro: Bulking ou Cutting?",
      "url": "https://www.youtube.com/watch?v=Wrr4t7aYMqA"
    },
    {
      "id": 35,
      "categoriaId": 5,
      "titulo": "TREINEI COM O BIG RAMY! *o maior fisiculturista do mundo*",
      "url": "https://www.youtube.com/watch?v=zVZLEPn_LQM"
    },
    {
      "id": 36,
      "categoriaId": 5,
      "titulo": "Como corrigir as desproporções do seu corpo?",
      "url": "https://www.youtube.com/watch?v=K_nMfL9TXAI"
    },
    {
      "id": 37,
      "categoriaId": 6,
      "titulo": "Lionel Messi - 100 European goals",
      "url": "https://www.youtube.com/watch?v=N_VWtZ5oxlI"
    },
    {
      "id": 38,
      "categoriaId": 6,
      "titulo": "Top 100 Plays | 2019-20 NBA Season",
      "url": "https://www.youtube.com/watch?v=DsxxgJTXr8Y"
    },
    {
      "id": 39,
      "categoriaId": 6,
      "titulo": "Patriots vs. Rams | Super Bowl LIII Game Highlights",
      "url": "https://www.youtube.com/watch?v=usw9WiShXEs"
    },
    {
      "id": 40,
      "categoriaId": 6,
      "titulo": "All Home Runs from 2020 Opening Day!",
      "url": "https://www.youtube.com/watch?v=CERazrEJ4k4"
    },
    {
      "id": 41,
      "categoriaId": 6,
      "titulo": "Collin Morikawa’s winning highlights from the Workday Charity Open 2020",
      "url": "https://www.youtube.com/watch?v=OmCGRggPBr8"
    },
    {
      "id": 42,
      "categoriaId": 6,
      "titulo": "Melhores nocautes do UFC em 2020",
      "url": "https://www.youtube.com/watch?v=qmueGkNvIQU"
    },
    {
      "id": 43,
      "categoriaId": 6,
      "titulo": "2020 Styrian Grand Prix: Race Highlights",
      "url": "https://www.youtube.com/watch?v=IEB3jc22izI"
    }
  ]
}
